phoenix_ai_services/__init__.py
phoenix_ai_services/main.py
phoenix_ai_services/rag_controller.py
phoenix_ai_services/registry.py
phoenix_ai_services/tool_controller.py
phoenix_ai_services/tool_sandbox.py
phoenix_ai_services-0.2.7.0.dist-info/LICENSE
phoenix_ai_services-0.2.7.0.dist-info/METADATA
phoenix_ai_services-0.2.7.0.dist-info/WHEEL
phoenix_ai_services-0.2.7.0.dist-info/RECORD
