Metadata-Version: 2.3
Name: phoenix-ai-services
Version: 0.2.7.0
Summary: Unified RAG and Tool API Service for Phoenix Agentic AI Framework
License: MIT
Author: Your Name
Author-email: you@example.com
Requires-Python: >=3.9,<4.0
Classifier: License :: OSI Approved :: MIT License
Classifier: Programming Language :: Python :: 3
Classifier: Programming Language :: Python :: 3.9
Classifier: Programming Language :: Python :: 3.10
Classifier: Programming Language :: Python :: 3.11
Classifier: Programming Language :: Python :: 3.12
Classifier: Programming Language :: Python :: 3.13
Requires-Dist: fastapi (>=0.110,<0.111)
Requires-Dist: fastapi-mcp
Requires-Dist: phoenix-ai
Requires-Dist: uvicorn (>=0.27,<0.28)
